neural_network_implementation/__init__.py
neural_network_implementation/layers.py
neural_network_implementation/neural_network.py
neural_network_implementation-1.0.1.dist-info/METADATA
neural_network_implementation-1.0.1.dist-info/WHEEL
neural_network_implementation-1.0.1.dist-info/dependency_links.txt
neural_network_implementation-1.0.1.dist-info/top_level.txt
neural_network_implementation-1.0.1.dist-info/RECORD
