Metadata-Version: 2.1
Name: neural-network-implementation
Version: 1.0.1
Summary: A neural network implementation.
Home-page: https://github.com/arif-x/neural-network-implementation
Author: Ariffudin
Author-email: sudo.ariffudin@email.com
License: MIT
Project-URL: Source, https://github.com/arif-x/neural-network-implementation
Project-URL: Source Code, https://github.com/arif-x/neural-network-implementation
Keywords: nn neural-network
Platform: UNKNOWN
Classifier: License :: OSI Approved :: MIT License
Classifier: Programming Language :: Python :: 3
Classifier: Programming Language :: Python :: 3.6
Classifier: Programming Language :: Python :: 3.7
Classifier: Programming Language :: Python :: 3.8
Classifier: Programming Language :: Python :: 3.9
Classifier: Programming Language :: Python :: 3.10
Classifier: Operating System :: OS Independent
Requires-Dist: nn-error-metrics
Requires-Dist: numpy
